{
  "Author": "Shirosaya25",
  "Name": "AutoResetActPlugin",
  "InternalName": "AutoResetActPlugin",
  "AssemblyVersion": "v0.1.1",
  "TestingAssemblyVersion": "v0.1.1",
  "Description": "The plugin will automatically execute the /echo end macro on encounter wipe",
  "ApplicableVersion": "any",
  "RepoUrl": "https://github.com/Shirosaya25/Plugins",
  "Tags": [
    "bully",
    "lazy",
    "media-tour"
  ],
  "DalamudApiLevel": 10,
  "IconUrl": "",
  "Punchline": "For lazy or forgetful people",
  "IsHide": "False",
  "IsTestingExclusive": "False",
  "DownloadLinkInstall": "https://github.com/Shirosaya25/Plugins/releases/download/v0.1.1/latest.zip",
  "DownloadLinkTesting": "https://github.com/Shirosaya25/Plugins/releases/download/v0.1.1/latest.zip",
  "DownloadLinkUpdate": "https://github.com/Shirosaya25/Plugins/releases/download/v0.1.1/latest.zip"
}